quantzsl/__init__.py
quantzsl/setup.py
quantzsl/untitled0.py
quantzsl/qz_backtest/__init__.py
quantzsl/qz_backtest/multi_stock_backtest.py
quantzsl/qz_backtest/qifi_test.py
quantzsl/qz_backtest/single_stock_backtest.py
quantzsl/qz_backtest/stock_backtest_base.py
quantzsl/qz_backtest/stock_min_backtest_base.py
quantzsl/qz_backtest/test.py
quantzsl/qz_backtest/untitled2.py
quantzsl/qz_data/__init__.py
quantzsl/qz_data/qz_data.py
quantzsl/qz_data/qz_data_resample.py
quantzsl/qz_data/qz_download_tushare.py
quantzsl/qz_database/__init__.py
quantzsl/qz_database/qz_mongo.py
quantzsl/qz_database/qz_tusharepro.py
quantzsl/qz_factor/__init__.py
quantzsl/qz_factor/qz_factor.py
quantzsl/qz_factor/qz_query_factor.py
quantzsl/qz_fench/__init__.py
quantzsl/qz_fench/qz_eastmoney.py
quantzsl/qz_fench/qz_query.py
quantzsl/qz_fench/qz_tushare.py
quantzsl/qz_indicator/__init__.py
quantzsl/qz_indicator/indicator.py
quantzsl/qz_random_price/__init__.py
quantzsl/qz_random_price/qz_random_price.py
quantzsl/qz_random_price/qz_random_price_handle.py
quantzsl/qz_realtime_solution/__init__.py
quantzsl/qz_realtime_solution/qz_qahexo.py
quantzsl/qz_realtime_solution/qz_realtime_data.py
quantzsl/qz_realtime_solution/qz_realtime_tick_tdx - 副本.py
quantzsl/qz_realtime_solution/qz_realtime_tick_tdx.py
quantzsl/qz_realtime_solution/test_sub.py
quantzsl/qz_save/__init__.py
quantzsl/qz_save/qz_save_eastmoney.py
quantzsl/qz_save/qz_save_factor.py
quantzsl/qz_save/qz_save_tushare.py
quantzsl/qz_send/__init__.py
quantzsl/qz_send/qz_send_dingding.py
quantzsl/qz_send/qz_send_email.py
quantzsl/qz_send/qz_send_wechat.py
quantzsl/qz_study/__init__.py
quantzsl/qz_study/houchuli.py
quantzsl/qz_study/houchuli_bt.py
quantzsl/qz_study/houchuli_sm.py
quantzsl/qz_study/qz_analysis.py
quantzsl/qz_study/qz_select.py
quantzsl/qz_trade/__init__.py
quantzsl/qz_trade/puppet_runer.py
quantzsl/qz_trade/puppet_test.py
quantzsl/qz_trade/puppet_test_WEB.py
quantzsl/qz_trade/simulate_etf_60min_ma_single.py
quantzsl-1.1.4.dist-info/LICENSE
quantzsl-1.1.4.dist-info/METADATA
quantzsl-1.1.4.dist-info/WHEEL
quantzsl-1.1.4.dist-info/entry_points.txt
quantzsl-1.1.4.dist-info/top_level.txt
quantzsl-1.1.4.dist-info/RECORD
