Metadata-Version: 2.1
Name: quantzsl
Version: 1.1.4
Summary: 梓昱zsl的quant
Home-page: UNKNOWN
Author: ziyu
Author-email: 303466906@qq.com
License: MIT Licence
Keywords: quant,trade
Platform: any
Requires-Dist: QUANTAXIS
